docts/__init__.py
docts/__main__.py
docts-0.2.3.dist-info/LICENSE
docts-0.2.3.dist-info/METADATA
docts-0.2.3.dist-info/WHEEL
docts-0.2.3.dist-info/entry_points.txt
docts-0.2.3.dist-info/top_level.txt
docts-0.2.3.dist-info/RECORD
