Metadata-Version: 2.1
Name: docts
Version: 0.2.3
Summary: python package docts
Author: foyoux
Project-URL: Source, https://github.com/foyoux/docts
Project-URL: Homepage, https://github.com/foyoux/docts
Project-URL: Bug Tracker, https://github.com/foyoux/docts/issues
Keywords: docts
Classifier: Programming Language :: Python
Classifier: Programming Language :: Python :: 3
Classifier: Programming Language :: Python :: 3.7
Classifier: Programming Language :: Python :: 3.8
Classifier: Programming Language :: Python :: 3.9
Classifier: Programming Language :: Python :: 3.10
Classifier: Programming Language :: Python :: 3.11
Requires-Python: >=3.7
License-File: LICENSE
Requires-Dist: pygtrans
